pytwebl/COLORS.py
pytwebl/__init__.py
pytwebl/main.py
pytwebl-1.0.3.dist-info/LICENSE
pytwebl-1.0.3.dist-info/METADATA
pytwebl-1.0.3.dist-info/WHEEL
pytwebl-1.0.3.dist-info/entry_points.txt
pytwebl-1.0.3.dist-info/top_level.txt
pytwebl-1.0.3.dist-info/RECORD
