Metadata-Version: 2.1
Name: pytwebl
Version: 1.0.3
Summary: Creates template for web-development from shell, includes : html, css and js.
Home-page: https://github.com/SoumadeepChoudhury/pytwebl
Author: Ahens | An Initiative to Initial (Soumadeep Choudhury)
Author-email: ahensinitiative@gmail.com
Maintainer: Manmay Chakraborty
Maintainer-email: manmaycoder@gmail.com
License: MIT
Classifier: Development Status :: 5 - Production/Stable
Classifier: Intended Audience :: Developers
Classifier: License :: OSI Approved :: MIT License
Classifier: Programming Language :: Python :: 3
Classifier: Programming Language :: Python :: 3.11
Classifier: Operating System :: Unix
Classifier: Operating System :: MacOS :: MacOS X
Classifier: Operating System :: Microsoft :: Windows
License-File: LICENSE
